TLC/TLcontroller.v
module TLcontroller(
    input clk, clear,
    output reg RED_NS, YELLOW_NS, GREEN_NS, RED_WE, YELLOW_WE, GREEN_WE
    );

    reg [2:0]current_state;
    reg [32:0]timer;

    parameter NS_MOVE = 3'b000;
    parameter NS_WAIT = 3'b001;
    parameter NS_ALL_RED = 3'b010;
    parameter WE_MOVE = 3'b011;
    parameter WE_WAIT = 3'b100;
    parameter WE_ALL_RED = 3'b101;

    always @(*)begin
        case (current_state)
            NS_MOVE: begin
                RED_NS =  1'b0;
                YELLOW_NS =  1'b0;
                GREEN_NS =  1'b1;
                RED_WE =  1'b1;
                YELLOW_WE = 1'b0;
                GREEN_WE = 1'b0;
            end
            NS_WAIT: begin
                RED_NS = 1'b0;
                YELLOW_NS = 1'b1;
                GREEN_NS = 1'b0;
                RED_WE = 1'b1;
                YELLOW_WE = 1'b0;
                GREEN_WE = 1'b0;
            end
            NS_ALL_RED: begin
                RED_NS = 1'b1;
                YELLOW_NS = 1'b0;
                GREEN_NS = 1'b0;
                RED_WE = 1'b1;
                YELLOW_WE = 1'b0;
                GREEN_WE = 1'b0;
            end
            WE_MOVE: begin
                RED_NS = 1'b1;
                YELLOW_NS = 1'b0;
                GREEN_NS = 1'b0;
                RED_WE = 1'b0;
                YELLOW_WE = 1'b0;
                GREEN_WE = 1'b1;
            end
            WE_WAIT: begin
                RED_NS = 1'b1;
                YELLOW_NS = 1'b0;
                GREEN_NS = 1'b0;
                RED_WE = 1'b0;
                YELLOW_WE = 1'b1;
                GREEN_WE = 1'b0;
            end
            WE_ALL_RED: begin
                RED_NS = 1'b1;
                YELLOW_NS = 1'b0;
                GREEN_NS = 1'b0;
                RED_WE = 1'b1;
                YELLOW_WE = 1'b0;
                GREEN_WE = 1'b0;
            end
            default: begin
                RED_NS = 1'b1;
                YELLOW_NS = 1'b0;
                GREEN_NS = 1'b0;
                RED_WE = 1'b1;
                YELLOW_WE = 1'b0;
                GREEN_WE = 1'b0;
            end
        endcase
    end

    always @(posedge clk or posedge clear)begin
        if (clear)begin
            current_state <= NS_ALL_RED;
            timer <= 0;
        end else begin
            case (current_state)
                NS_MOVE: begin
                    if (timer == 29) begin
                        current_state <= NS_WAIT;
                        timer <= 0;
                    end else begin
                        timer <= timer + 1;
                    end
                end
                NS_WAIT: begin
                    if (timer == 3) begin
                        current_state <= NS_ALL_RED;
                        timer <= 0;
                    end else begin
                        timer <= timer + 1;
                    end
                end
                NS_ALL_RED: begin
                    if (timer == 3)begin
                        current_state <= WE_MOVE;
                        timer <= 0;
                    end else begin
                        timer <= timer + 1;
                    end
                end
                WE_MOVE: begin
                    if (timer == 29)begin
                        current_state <= WE_WAIT;
                        timer <= 0;
                    end else begin
                        timer <= timer + 1;
                    end
                end
                WE_WAIT: begin
                    if (timer == 3)begin
                        current_state <= WE_ALL_RED;
                        timer <= 0;
                    end else begin
                        timer <= timer + 1;
                    end
                end
                WE_ALL_RED: begin
                    if (timer == 3)begin
                        current_state <= NS_MOVE;
                        timer <= 0;
                    end else begin
                        timer <= timer + 1;
                    end
                end
            endcase
        end
    end
endmodule

TLC/tb_TLcontroller.v
`timescale 1ns/1ps

module tb_TLcontroller();
    reg clk;
    reg clear;
    wire RED_NS;
    wire YELLOW_NS;
    wire GREEN_NS;
    wire RED_WE;
    wire YELLOW_WE;
    wire GREEN_WE;

    TLcontroller uut (
        .clk(clk),
        .clear(clear),
        .RED_NS(RED_NS),
        .YELLOW_NS(YELLOW_NS),
        .GREEN_NS(GREEN_NS),
        .RED_WE(RED_WE),
        .YELLOW_WE(YELLOW_WE),
        .GREEN_WE(GREEN_WE)
        );

        initial clk = 1'b0;

        always #5 clk = ~clk;

        initial begin
            $dumpfile("controller_waveform.vcd");
            $dumpvars(0, tb_TLcontroller);

            clear = 1'b1;
            #20;

            clear = 1'b0;
            #760;

            #760;

            clear = 1'b1;
            #20;

            $finish;
        end
endmodule;

controller_waveform.vcd
$date
	Sun Oct 19 23:23:59 2025
$end
$version
	Icarus Verilog
$end
$timescale
	1ps
$end
$scope module tb_TLcontroller $end
$var wire 1 ! YELLOW_WE $end
$var wire 1 " YELLOW_NS $end
$var wire 1 # RED_WE $end
$var wire 1 $ RED_NS $end
$var wire 1 % GREEN_WE $end
$var wire 1 & GREEN_NS $end
$var reg 1 ' clear $end
$var reg 1 ( clk $end
$scope module uut $end
$var wire 1 ' clear $end
$var wire 1 ( clk $end
$var parameter 3 ) NS_ALL_RED $end
$var parameter 3 * NS_MOVE $end
$var parameter 3 + NS_WAIT $end
$var parameter 3 , WE_ALL_RED $end
$var parameter 3 - WE_MOVE $end
$var parameter 3 . WE_WAIT $end
$var reg 1 & GREEN_NS $end
$var reg 1 % GREEN_WE $end
$var reg 1 $ RED_NS $end
$var reg 1 # RED_WE $end
$var reg 1 " YELLOW_NS $end
$var reg 1 ! YELLOW_WE $end
$var reg 3 / current_state [2:0] $end
$var reg 33 0 timer [32:0] $end
$upscope $end
$upscope $end
$enddefinitions $end
$comment Show the parameter values. $end
$dumpall
b100 .
b11 -
b101 ,
b1 +
b0 *
b10 )
$end
#0
$dumpvars
b0 0
b10 /
0(
1'
0&
0%
1$
1#
0"
0!
$end
#5000
1(
#10000
0(
#15000
1(
#20000
0(
0'
#25000
b1 0
1(
#30000
0(
#35000
b10 0
1(
#40000
0(
#45000
b11 0
1(
#50000
0(
#55000
1%
0#
b0 0
b11 /
1(
#60000
0(
#65000
b1 0
1(
#70000
0(
#75000
b10 0
1(
#80000
0(
#85000
b11 0
1(
#90000
0(
#95000
b100 0
1(
#100000
0(
#105000
b101 0
1(
#110000
0(
#115000
b110 0
1(
#120000
0(
#125000
b111 0
1(
#130000
0(
#135000
b1000 0
1(
#140000
0(
#145000
b1001 0
1(
#150000
0(
#155000
b1010 0
1(
#160000
0(
#165000
b1011 0
1(
#170000
0(
#175000
b1100 0
1(
#180000
0(
#185000
b1101 0
1(
#190000
0(
#195000
b1110 0
1(
#200000
0(
#205000
b1111 0
1(
#210000
0(
#215000
b10000 0
1(
#220000
0(
#225000
b10001 0
1(
#230000
0(
#235000
b10010 0
1(
#240000
0(
#245000
b10011 0
1(
#250000
0(
#255000
b10100 0
1(
#260000
0(
#265000
b10101 0
1(
#270000
0(
#275000
b10110 0
1(
#280000
0(
#285000
b10111 0
1(
#290000
0(
#295000
b11000 0
1(
#300000
0(
#305000
b11001 0
1(
#310000
0(
#315000
b11010 0
1(
#320000
0(
#325000
b11011 0
1(
#330000
0(
#335000
b11100 0
1(
#340000
0(
#345000
b11101 0
1(
#350000
0(
#355000
0%
1!
b0 0
b100 /
1(
#360000
0(
#365000
b1 0
1(
#370000
0(
#375000
b10 0
1(
#380000
0(
#385000
b11 0
1(
#390000
0(
#395000
0!
1#
b0 0
b101 /
1(
#400000
0(
#405000
b1 0
1(
#410000
0(
#415000
b10 0
1(
#420000
0(
#425000
b11 0
1(
#430000
0(
#435000
1&
0$
b0 0
b0 /
1(
#440000
0(
#445000
b1 0
1(
#450000
0(
#455000
b10 0
1(
#460000
0(
#465000
b11 0
1(
#470000
0(
#475000
b100 0
1(
#480000
0(
#485000
b101 0
1(
#490000
0(
#495000
b110 0
1(
#500000
0(
#505000
b111 0
1(
#510000
0(
#515000
b1000 0
1(
#520000
0(
#525000
b1001 0
1(
#530000
0(
#535000
b1010 0
1(
#540000
0(
#545000
b1011 0
1(
#550000
0(
#555000
b1100 0
1(
#560000
0(
#565000
b1101 0
1(
#570000
0(
#575000
b1110 0
1(
#580000
0(
#585000
b1111 0
1(
#590000
0(
#595000
b10000 0
1(
#600000
0(
#605000
b10001 0
1(
#610000
0(
#615000
b10010 0
1(
#620000
0(
#625000
b10011 0
1(
#630000
0(
#635000
b10100 0
1(
#640000
0(
#645000
b10101 0
1(
#650000
0(
#655000
b10110 0
1(
#660000
0(
#665000
b10111 0
1(
#670000
0(
#675000
b11000 0
1(
#680000
0(
#685000
b11001 0
1(
#690000
0(
#695000
b11010 0
1(
#700000
0(
#705000
b11011 0
1(
#710000
0(
#715000
b11100 0
1(
#720000
0(
#725000
b11101 0
1(
#730000
0(
#735000
0&
1"
b0 0
b1 /
1(
#740000
0(
#745000
b1 0
1(
#750000
0(
#755000
b10 0
1(
#760000
0(
#765000
b11 0
1(
#770000
0(
#775000
0"
1$
b0 0
b10 /
1(
#780000
0(
#785000
b1 0
1(
#790000
0(
#795000
b10 0
1(
#800000
0(
#805000
b11 0
1(
#810000
0(
#815000
1%
0#
b0 0
b11 /
1(
#820000
0(
#825000
b1 0
1(
#830000
0(
#835000
b10 0
1(
#840000
0(
#845000
b11 0
1(
#850000
0(
#855000
b100 0
1(
#860000
0(
#865000
b101 0
1(
#870000
0(
#875000
b110 0
1(
#880000
0(
#885000
b111 0
1(
#890000
0(
#895000
b1000 0
1(
#900000
0(
#905000
b1001 0
1(
#910000
0(
#915000
b1010 0
1(
#920000
0(
#925000
b1011 0
1(
#930000
0(
#935000
b1100 0
1(
#940000
0(
#945000
b1101 0
1(
#950000
0(
#955000
b1110 0
1(
#960000
0(
#965000
b1111 0
1(
#970000
0(
#975000
b10000 0
1(
#980000
0(
#985000
b10001 0
1(
#990000
0(
#995000
b10010 0
1(
#1000000
0(
#1005000
b10011 0
1(
#1010000
0(
#1015000
b10100 0
1(
#1020000
0(
#1025000
b10101 0
1(
#1030000
0(
#1035000
b10110 0
1(
#1040000
0(
#1045000
b10111 0
1(
#1050000
0(
#1055000
b11000 0
1(
#1060000
0(
#1065000
b11001 0
1(
#1070000
0(
#1075000
b11010 0
1(
#1080000
0(
#1085000
b11011 0
1(
#1090000
0(
#1095000
b11100 0
1(
#1100000
0(
#1105000
b11101 0
1(
#1110000
0(
#1115000
0%
1!
b0 0
b100 /
1(
#1120000
0(
#1125000
b1 0
1(
#1130000
0(
#1135000
b10 0
1(
#1140000
0(
#1145000
b11 0
1(
#1150000
0(
#1155000
0!
1#
b0 0
b101 /
1(
#1160000
0(
#1165000
b1 0
1(
#1170000
0(
#1175000
b10 0
1(
#1180000
0(
#1185000
b11 0
1(
#1190000
0(
#1195000
1&
0$
b0 0
b0 /
1(
#1200000
0(
#1205000
b1 0
1(
#1210000
0(
#1215000
b10 0
1(
#1220000
0(
#1225000
b11 0
1(
#1230000
0(
#1235000
b100 0
1(
#1240000
0(
#1245000
b101 0
1(
#1250000
0(
#1255000
b110 0
1(
#1260000
0(
#1265000
b111 0
1(
#1270000
0(
#1275000
b1000 0
1(
#1280000
0(
#1285000
b1001 0
1(
#1290000
0(
#1295000
b1010 0
1(
#1300000
0(
#1305000
b1011 0
1(
#1310000
0(
#1315000
b1100 0
1(
#1320000
0(
#1325000
b1101 0
1(
#1330000
0(
#1335000
b1110 0
1(
#1340000
0(
#1345000
b1111 0
1(
#1350000
0(
#1355000
b10000 0
1(
#1360000
0(
#1365000
b10001 0
1(
#1370000
0(
#1375000
b10010 0
1(
#1380000
0(
#1385000
b10011 0
1(
#1390000
0(
#1395000
b10100 0
1(
#1400000
0(
#1405000
b10101 0
1(
#1410000
0(
#1415000
b10110 0
1(
#1420000
0(
#1425000
b10111 0
1(
#1430000
0(
#1435000
b11000 0
1(
#1440000
0(
#1445000
b11001 0
1(
#1450000
0(
#1455000
b11010 0
1(
#1460000
0(
#1465000
b11011 0
1(
#1470000
0(
#1475000
b11100 0
1(
#1480000
0(
#1485000
b11101 0
1(
#1490000
0(
#1495000
0&
1"
b0 0
b1 /
1(
#1500000
0(
#1505000
b1 0
1(
#1510000
0(
#1515000
b10 0
1(
#1520000
0(
#1525000
b11 0
1(
#1530000
0(
#1535000
0"
1$
b0 0
b10 /
1(
#1540000
0(
1'
