Johnson4bit.v
module Johnson4bit(
    input clk, clear, en, count_mode,
    output reg [3:0] q_out
    );
    always @(posedge clk or posedge clear)begin
        if (clear) begin
            q_out <= 4'b0;
        end else begin
            if (en) begin
                if (count_mode)begin
                    q_out <= {q_out[2:0], ~q_out[3]};
                end else begin
                    q_out <= {~q_out[0], q_out[3:1]};
                end
            end else begin
                q_out <= q_out;
            end
        end
    end
endmodule;


// Notable problem faced:

//When I tried to feed Q3 to D0 instead of my current down counting style, it got forever stuck at 0000
// It kept puttng 000 and 0 together, so the counter did not proceed and got stuck in a single state
//The current down counting method is the correct way, instead of shifting left and adding Q3 to D0

tb_Johnson4bit.v
`timescale 1ns/1ps

module tb_Johnson4bit();
    reg clk;
    reg clear;
    reg en;
    reg count_mode;
    wire [3:0]q_out;

    Johnson4bit uut (
        .clk(clk),
        .clear(clear),
        .en(en),
        .count_mode(count_mode),
        .q_out(q_out)
        );

        initial clk = 1'b0;

        always #5 clk = ~clk;

        initial begin
            $dumpfile("counter_waveform.vcd");
            $dumpvars(0, tb_Johnson4bit);

            clear = 1'b1;
            en = 1'b0;
            count_mode = 1'b0;
            #10;

            clear = 1'b0;
            en = 1'b1;
            count_mode = 1'b1;
            #80; //Counter ko chalne do, 8 total states hai, 10 ns ek clock cycle hai, to total 80 ns wait krna hoga

            en = 1'b0;
            #20;

            en = 1'b1;
            count_mode = 1'b0;
            #80;

            clear = 1'b1;
            #20;

            clear = 1'b0;
            en = 1'b0;
            #20;

            $finish;
        end
endmodule

counter_waveform.vcd
$date
	Sat Oct 18 21:37:27 2025
$end
$version
	Icarus Verilog
$end
$timescale
	1ps
$end
$scope module tb_Johnson4bit $end
$var wire 4 ! q_out [3:0] $end
$var reg 1 " clear $end
$var reg 1 # clk $end
$var reg 1 $ count_mode $end
$var reg 1 % en $end
$scope module uut $end
$var wire 1 " clear $end
$var wire 1 # clk $end
$var wire 1 $ count_mode $end
$var wire 1 % en $end
$var reg 4 & q_out [3:0] $end
$upscope $end
$upscope $end
$enddefinitions $end
$comment Show the parameter values. $end
$dumpall
$end
#0
$dumpvars
b0 &
0%
0$
0#
1"
b0 !
$end
#5000
1#
#10000
0#
1$
1%
0"
#15000
b1 !
b1 &
1#
#20000
0#
#25000
b11 !
b11 &
1#
#30000
0#
#35000
b111 !
b111 &
1#
#40000
0#
#45000
b1111 !
b1111 &
1#
#50000
0#
#55000
b1110 !
b1110 &
1#
#60000
0#
#65000
b1100 !
b1100 &
1#
#70000
0#
#75000
b1000 !
b1000 &
1#
#80000
0#
#85000
b0 !
b0 &
1#
#90000
0#
0%
#95000
1#
#100000
0#
#105000
1#
#110000
0#
0$
1%
#115000
b1000 !
b1000 &
1#
#120000
0#
#125000
b1100 !
b1100 &
1#
#130000
0#
#135000
b1110 !
b1110 &
1#
#140000
0#
#145000
b1111 !
b1111 &
1#
#150000
0#
#155000
b111 !
b111 &
1#
#160000
0#
#165000
b11 !
b11 &
1#
#170000
0#
#175000
b1 !
b1 &
1#
#180000
0#
#185000
b0 !
b0 &
1#
#190000
0#
1"
#195000
1#
#200000
0#
#205000
1#
#210000
0#
0%
0"
