LEDblinker.v
// Will blink LED on and OFF every 0.5 seconds that is 24,999,999

module LEDblinker(
    input clk, clear,
    output reg led_out
    );

    parameter MAX_COUNT = 24_999_999;

    reg [$clog2(MAX_COUNT + 1)-1:0]counter_flag;

    always @(posedge clk or posedge clear)begin
        if (clear)begin
            counter_flag <= 0;
            led_out <= 1'b0;
        end else begin
            if (counter_flag == MAX_COUNT)begin
                led_out <= ~led_out;
                counter_flag <= 0;
            end else begin
                led_out <= led_out;
                counter_flag <= counter_flag + 1;
            end
        end
    end
endmodule


// clog2 is a built in function of verilog that automatically calculates the total amount of bits needed to store a particular value
// But clog2 would suppose give 8 for both 7 and 8
// That is the reason I did MAX_COUNT + 1
// Since this gives a totaL OF 25 BITS i ALSO DID -1 because we are starting from 0

tb_LEDblinker.v
`timescale 1ns/1ps

module tb_LEDblinker();
    reg clk;
    reg clear;
    wire led_out;

    LEDblinker uut (
        .clk(clk),
        .clear(clear),
        .led_out(led_out)
        );

        initial clk = 1'b0;

        always #5 clk = ~clk;

        initial begin
            $dumpfile("LEDwaveform.vcd");
            $dumpvars(0, tb_LEDblinker);

            clear = 1'b1;
            #20;

            clear = 1'b0;
            #40;
            //LED turns on

            #40; //LED turns off

            clear = 1'b1;
            #20; 
            $finish;
        end
endmodule

LEDwaveform.vcd
$date
	Sat Oct 18 22:32:08 2025
$end
$version
	Icarus Verilog
$end
$timescale
	1ps
$end
$scope module tb_LEDblinker $end
$var wire 1 ! led_out $end
$var reg 1 " clear $end
$var reg 1 # clk $end
$scope module uut $end
$var wire 1 " clear $end
$var wire 1 # clk $end
$var reg 25 $ counter_flag [24:0] $end
$var reg 1 ! led_out $end
$upscope $end
$upscope $end
$enddefinitions $end
$comment Show the parameter values. $end
$dumpall
$end
#0
$dumpvars
b0 $
0#
1"
0!
$end
#5000
1#
#10000
0#
#15000
1#
#20000
0#
0"
#25000
b1 $
1#
#30000
0#
#35000
b10 $
1#
#40000
0#
#45000
b11 $
1#
#50000
0#
#55000
b100 $
1#
#60000
0#
#65000
b0 $
1!
1#
#70000
0#
#75000
b1 $
1#
#80000
0#
#85000
b10 $
1#
#90000
0#
#95000
b11 $
1#
#100000
0!
b0 $
0#
1"
