tlc_oneway.v
//RED: 4 ns
//YELLOW: 2 ns
//GREEN: 4 ns

module tlc_oneway(
    input clear, clk,
    output reg RED_out, YELLOW_out, GREEN_out
    );

    reg [1:0] current_state;
    reg [7:0] timer;

    parameter RED = 2'b00;
    parameter YELLOW = 2'b01;
    parameter GREEN = 2'b10;

    always @(*)begin
        case (current_state)
            RED: begin
                RED_out = 1'b1;
                YELLOW_out = 1'b0;
                GREEN_out = 1'b0;
            end
            YELLOW: begin
                RED_out = 1'b0;
                YELLOW_out = 1'b1;
                GREEN_out = 1'b0;
            end
            GREEN: begin
                RED_out = 1'b0;
                YELLOW_out = 1'b0;
                GREEN_out = 1'b1;
            end
            default: begin
                RED_out = 1'b0;
                YELLOW_out = 1'b0;
                GREEN_out = 1'b0;
            end
        endcase
    end

    always @(posedge clk or posedge clear)begin
        if (clear) begin
            current_state <= RED;
            timer <= 8'b0;
        end else begin
            case (current_state)
                RED: begin
                    if (timer == 8'd3)begin
                        current_state <= GREEN;
                        timer <= 8'd0;
                    end else begin
                        timer <= timer + 1;
                    end
                end
                YELLOW: begin
                    if (timer == 8'd1)begin
                        current_state <= RED;
                        timer <= 8'd0;
                    end else begin
                        timer <= timer + 1;
                    end
                end
                GREEN: begin
                    if (timer == 8'd3)begin
                        current_state <= YELLOW;
                        timer <= 8'd0;
                    end else begin
                        timer <= timer + 1;
                    end
                end
            endcase
        end
    end
endmodule;

tb_tlc_oneway.v
`timescale 1ns/1ps

module tb_tlc_oneway();
    reg clk;
    reg clear;
    wire RED_out;
    wire YELLOW_out;
    wire GREEN_out;

    tlc_oneway uut (
        .clk(clk),
        .clear(clear),
        .RED_out(RED_out),
        .YELLOW_out(YELLOW_out),
        .GREEN_out(GREEN_out)
        );

        initial clk = 1'b0;

        always #5 clk = ~clk;

        initial begin
            $dumpfile("oneway_waveform.vcd");
            $dumpvars(0, tb_tlc_oneway);

            clear = 1'b1;
            #20;

            clear = 1'b0;
            
            #200;

            clear = 1'b1;
            #20;

            $finish;
        end
endmodule;

oneway_waveform.vcd
$date
	Sun Oct 19 00:00:11 2025
$end
$version
	Icarus Verilog
$end
$timescale
	1ps
$end
$scope module tb_tlc_oneway $end
$var wire 1 ! YELLOW_out $end
$var wire 1 " RED_out $end
$var wire 1 # GREEN_out $end
$var reg 1 $ clear $end
$var reg 1 % clk $end
$scope module uut $end
$var wire 1 $ clear $end
$var wire 1 % clk $end
$var parameter 2 & GREEN $end
$var parameter 2 ' RED $end
$var parameter 2 ( YELLOW $end
$var reg 1 # GREEN_out $end
$var reg 1 " RED_out $end
$var reg 1 ! YELLOW_out $end
$var reg 2 ) current_state [1:0] $end
$var reg 8 * timer [7:0] $end
$upscope $end
$upscope $end
$enddefinitions $end
$comment Show the parameter values. $end
$dumpall
b1 (
b0 '
b10 &
$end
#0
$dumpvars
b0 *
b0 )
0%
1$
0#
1"
0!
$end
#5000
1%
#10000
0%
#15000
1%
#20000
0%
0$
#25000
b1 *
1%
#30000
0%
#35000
b10 *
1%
#40000
0%
#45000
b11 *
1%
#50000
0%
#55000
1#
0"
b0 *
b10 )
1%
#60000
0%
#65000
b1 *
1%
#70000
0%
#75000
b10 *
1%
#80000
0%
#85000
b11 *
1%
#90000
0%
#95000
0#
1!
b0 *
b1 )
1%
#100000
0%
#105000
b1 *
1%
#110000
0%
#115000
0!
1"
b0 *
b0 )
1%
#120000
0%
#125000
b1 *
1%
#130000
0%
#135000
b10 *
1%
#140000
0%
#145000
b11 *
1%
#150000
0%
#155000
1#
0"
b0 *
b10 )
1%
#160000
0%
#165000
b1 *
1%
#170000
0%
#175000
b10 *
1%
#180000
0%
#185000
b11 *
1%
#190000
0%
#195000
0#
1!
b0 *
b1 )
1%
#200000
0%
#205000
b1 *
1%
#210000
0%
#215000
0!
1"
b0 *
b0 )
1%
#220000
0%
1$
