moore_SD.v
module moore_SD(
    input clk, clear, in,
    output reg out
    );

    parameter S0 = 3'b000; // Initial
    parameter S1 = 3'b001; // 1
    parameter S2 = 3'b010; // 10
    parameter S3 = 3'b011; // 101
    parameter S4 = 3'b100; // 1011

    reg [2:0]currentState;
    reg [2:0]nextState;

    // Block to handle State transitions
    always @(posedge clk or posedge clear)begin
        if (clear)begin
            currentState <= S0;
        end else begin
            currentState <= nextState;
        end
    end

    // Block to determne next state based on current state and input
    always @(*)begin
        case (currentState)
            S0: nextState = (in == 1'b1)? S1: S0;  
            S1: nextState = (in == 1'b1)? S1: S2; 
            S2: nextState = (in == 1'b1)? S3: S0;  
            S3: nextState = (in == 1'b1)? S4: S0;  
            S4: nextState = (in == 1'b1)? S1: S0;
            default: nextState = S0; 
        endcase
    end

    // Block to determine the moore output which depends only on the current state
    always @(*)begin
        if (currentState == S4)begin
            out = 1'b1;
        end else begin
            out = 1'b0;
        end
    end

endmodule

tb_moore_SD.v
`timescale 1ns/1ps

module tb_moore_SD();
    reg clk;
    reg in;
    reg clear;
    wire out;

    moore_SD uut (
        .clk(clk),
        .in(in),
        .clear(clear),
        .out(out)
    );

    initial clk = 1'b0;
    
    always #5 clk = ~clk;

    initial begin //Test input: 1011001011
        $dumpfile("waveform1011.vcd");
        $dumpvars(0, tb_moore_SD);

        clear = 1'b1; in = 1'b0; #10;
        $display("CLEAR = %b || IN = %b || OUT = %b", clear, in, out);

        clear = 1'b0; #10;
        $display("CLEAR = %b || IN = %b || OUT = %b", clear, in, out);

        in = 1'b1; #10;
        $display("CLEAR = %b || IN = %b || OUT = %b", clear, in, out);
        in = 1'b0; #10;
        $display("CLEAR = %b || IN = %b || OUT = %b", clear, in, out);
        in = 1'b1; #10;
        $display("CLEAR = %b || IN = %b || OUT = %b", clear, in, out);
        in = 1'b1; #10;
        $display("CLEAR = %b || IN = %b || OUT = %b", clear, in, out);

        in = 1'b0; #10;
        $display("CLEAR = %b || IN = %b || OUT = %b", clear, in, out);
        in = 1'b0; #10;
        $display("CLEAR = %b || IN = %b || OUT = %b", clear, in, out);

        in = 1'b1; #10;
        $display("CLEAR = %b || IN = %b || OUT = %b", clear, in, out);
        in = 1'b0; #10;
        $display("CLEAR = %b || IN = %b || OUT = %b", clear, in, out);
        in = 1'b1; #10;
        $display("CLEAR = %b || IN = %b || OUT = %b", clear, in, out);
        in = 1'b1; #10;
        $display("CLEAR = %b || IN = %b || OUT = %b", clear, in, out);

        clear = 1'b1; #10;
        $display("CLEAR = %b || IN = %b || OUT = %b", clear, in, out);

        $finish;
    end
endmodule

waveform1011.vcd
$date
	Wed Oct 08 19:29:52 2025
$end
$version
	Icarus Verilog
$end
$timescale
	1ps
$end
$scope module tb_moore_SD $end
$var wire 1 ! out $end
$var reg 1 " clear $end
$var reg 1 # clk $end
$var reg 1 $ in $end
$scope module uut $end
$var wire 1 " clear $end
$var wire 1 # clk $end
$var wire 1 $ in $end
$var parameter 3 % S0 $end
$var parameter 3 & S1 $end
$var parameter 3 ' S2 $end
$var parameter 3 ( S3 $end
$var parameter 3 ) S4 $end
$var reg 3 * currentState [2:0] $end
$var reg 3 + nextState [2:0] $end
$var reg 1 ! out $end
$upscope $end
$upscope $end
$enddefinitions $end
$comment Show the parameter values. $end
$dumpall
b100 )
b11 (
b10 '
b1 &
b0 %
$end
#0
$dumpvars
b0 +
b0 *
0$
0#
1"
0!
$end
#5000
1#
#10000
0#
0"
#15000
1#
#20000
b1 +
0#
1$
#25000
b1 *
1#
#30000
b10 +
0#
0$
#35000
b0 +
b10 *
1#
#40000
b11 +
0#
1$
#45000
b100 +
b11 *
1#
#50000
0#
#55000
1!
b1 +
b100 *
1#
#60000
b0 +
0#
0$
#65000
0!
b0 *
1#
#70000
0#
#75000
1#
#80000
b1 +
0#
1$
#85000
b1 *
1#
#90000
b10 +
0#
0$
#95000
b0 +
b10 *
1#
#100000
b11 +
0#
1$
#105000
b100 +
b11 *
1#
#110000
0#
#115000
1!
b1 +
b100 *
1#
#120000
0!
b0 *
0#
1"
